eansearch.py
eansearch-1.9.0.dist-info/licenses/LICENSE
eansearch-1.9.0.dist-info/METADATA
eansearch-1.9.0.dist-info/WHEEL
eansearch-1.9.0.dist-info/top_level.txt
eansearch-1.9.0.dist-info/RECORD
