Metadata-Version: 2.4
Name: eansearch
Version: 1.9.0
Summary: A Python class for EAN and ISBN name lookup and validation using the API on ean-search.org
Home-page: https://github.com/eansearch/python-ean-search
Author: Jan Willamowius
Author-email: info@relaxedcommunications.com
Keywords: barcode barcodes ean ean13 ean-13 upc gtin isbn13 isbn-13 search lookup find valid validation
Classifier: License :: OSI Approved
Classifier: License :: OSI Approved :: MIT License
Classifier: Development Status :: 5 - Production/Stable
Classifier: Intended Audience :: Developers
Classifier: Intended Audience :: Other Audience
Classifier: Programming Language :: Python :: 2
Classifier: Programming Language :: Python :: 3
Classifier: Operating System :: OS Independent
Classifier: Operating System :: MacOS
Classifier: Operating System :: Microsoft :: Windows
Classifier: Operating System :: POSIX
Classifier: Operating System :: Unix
Classifier: Programming Language :: Python
Classifier: Topic :: Office/Business :: Financial :: Point-Of-Sale
Classifier: Topic :: Software Development :: Libraries
Classifier: Topic :: Software Development :: Libraries :: Python Modules
Requires-Python: >=2.0
License-File: LICENSE
Dynamic: author
Dynamic: author-email
Dynamic: classifier
Dynamic: description
Dynamic: description-content-type
Dynamic: home-page
Dynamic: keywords
Dynamic: license-file
Dynamic: requires-python
Dynamic: summary
